pypkgs_524_ind1/__init__.py
pypkgs_524_ind1/pypkgs_524_ind1.py
pypkgs_524_ind1-0.1.0.dist-info/LICENSE
pypkgs_524_ind1-0.1.0.dist-info/WHEEL
pypkgs_524_ind1-0.1.0.dist-info/METADATA
pypkgs_524_ind1-0.1.0.dist-info/RECORD
