Metadata-Version: 2.1
Name: pypkgs-524-ind1
Version: 0.1.0
Summary: 
License: MIT
Author: yzr96
Author-email: eric.yu@usask.ca
Requires-Python: >=3.8,<4.0
Classifier: License :: OSI Approved :: MIT License
Classifier: Programming Language :: Python :: 3
Classifier: Programming Language :: Python :: 3.8
Classifier: Programming Language :: Python :: 3.9
Requires-Dist: pandas (>=1.2.2,<2.0.0)
